README.txt
setup.cfg
setup.py
docs/HISTORY.txt
docs/INSTALL.txt
docs/LICENSE.GPL
docs/LICENSE.txt
mfabrik/__init__.py
mfabrik.like.egg-info/PKG-INFO
mfabrik.like.egg-info/SOURCES.txt
mfabrik.like.egg-info/dependency_links.txt
mfabrik.like.egg-info/entry_points.txt
mfabrik.like.egg-info/namespace_packages.txt
mfabrik.like.egg-info/not-zip-safe
mfabrik.like.egg-info/paster_plugins.txt
mfabrik.like.egg-info/requires.txt
mfabrik.like.egg-info/top_level.txt
mfabrik/like/.tmp_like.pt.89639~
mfabrik/like/__init__.py
mfabrik/like/configure.zcml
mfabrik/like/facebook-connect-head.pt
mfabrik/like/facebook-connect-loader-div.pt
mfabrik/like/interfaces.py
mfabrik/like/like-box-connect.pt
mfabrik/like/like-button-iframe.pt
mfabrik/like/locales.py
mfabrik/like/portlets.py
mfabrik/like/tests.py
mfabrik/like/viewlets.py
mfabrik/like/views.py
mfabrik/like/vocabularies.py
mfabrik/like/profiles/default/browserlayer.xml
mfabrik/like/profiles/default/controlpanel.xml
mfabrik/like/profiles/default/metadata.xml
mfabrik/like/profiles/default/portlets.xml
mfabrik/like/profiles/default/registry.xml