Metadata-Version: 1.0
Name: mfabrik.like
Version: 2.1
Summary: Facebook Like features and Connect API support for Plone. Because everybody loves Facebook (and mFabrik).
Home-page: http://mfabrik.com
Author: mFabrik Research Oy
Author-email: research@mfabrik.com
License: GPL
Keywords: facebook like plone viewlet portlet connect
Platform: UNKNOWN
Classifier: Framework :: Plone
Classifier: Programming Language :: Python
